[
    {
        "id": 1,
        "name": "Motherboard Repair",
        "price": "300",
        "description": "I offer motherboard checkup and repairing services of all brand including HP, DELL, ACER, LENOVO, TOSHIBA, SAMSUNG, APPLE and more.",
        "img": "https://img.freepik.com/free-photo/technician-repairing-computer-computer-hardware-repairing-upgrade-technology_1150-8859.jpg"
    },
    {
        "id": 2,
        "name": "HDD-SSD Data Recovery",
        "price": "200",
        "description": "I offer data recovery services for all type of internal and external storage drive such as hard disk drive, solid state drive, pen drives etc.",
        "img": "https://img.freepik.com/free-photo/hard-drive-disc-close-up_144627-9074.jpg"
    },
    {
        "id": 3,
        "name": "OS Install & Troubleshoot",
        "price": "150",
        "description": "I offer operating system installation and troubleshooting services of all variant such as Windows, Windows Server, Mac OS, Linux distro",
        "img": "https://img.freepik.com/free-photo/close-up-man-writing-code-laptop_158595-5169.jpg"
    },
    {
        "id": 4,
        "name": "Laptop Repair",
        "price": "250",
        "description": "I offer laptop repairing services of all brand including HP, DELL, ACER, LENOVO, TOSHIBA, SAMSUNG, APPLE and more.",
        "img": "https://img.freepik.com/free-photo/man-closes-topcase-metallic-slim-laptop-assemble-it-back-after-fixing-cleaning-repairing-service-his-lab_346278-1806.jpg?"
    },
    {
        "id": 5,
        "name": "Old System Upgrade",
        "price": "300",
        "description": "I offer old laptop, desktop and server pc system upgrade services including custom requirements and other criterias.",
        "img": "https://img.freepik.com/free-photo/technician-repairing-computer-computer-hardware-repairing-upgrade-technology_1150-8854.jpg"
    },
    {
        "id": 6,
        "name": "New System Build",
        "price": "250",
        "description": "I offer new system build services including custom build and all major brand like HP, DELL, ACER, LENOVO, TOSHIBA, SAMSUNG and more.",
        "img": "https://img.freepik.com/free-photo/computer_1205-719.jpg"
    },
    {
        "id": 7,
        "name": "CD-DVD Data Recovery",
        "price": "150",
        "description": "I offer data recovery services for all type of storage disk such as compact disk (CD) and digital versatile disc (DVD).",
        "img": "https://img.freepik.com/free-psd/cd-case-mockup_58466-10869.jpg"
    },
    {
        "id": 8,
        "name": "Power Supply Repair",
        "price": "200",
        "description": "I offer all type of power supply unit installation and repair services for laptops, desktops and servers systems.",
        "img": "https://www.gamingscan.com/wp-content/uploads/2019/03/picking-a-power-supply.jpg"
    },
    {
        "id": 9,
        "name": "Cooling System Install",
        "price": "250",
        "description": "I offer all type of cooling system components installation and checkup services for laptops, desktops and servers.",
        "img": "https://img.freepik.com/free-vector/cooling-system-design-concept_1284-45254.jpg"
    },
    {
        "id": 10,
        "name": "Printer & Photocopier Repair",
        "price": "200",
        "description": "I offer all type of printer & photocopier repairing services of all popular brands like Canon, Brother, HP, DELL, TOSHIBA, SAMSUNG, RICOH and more.",
        "img": "https://img.freepik.com/free-photo/home-printer-based-toner_23-2149287461.jpg"
    }
]